[
    {
        "id": "0t7B06Q8Lhd1dsCrliH7B0",
        "name": "In the Absence of Truth",
        "cover_image": "https://i.scdn.co/image/ab67616d00001e029f98e2b18ab3eb0e15a1c466",
        "popularity": 28,
        "release_date": "2006-10-31",
        "total_tracks": 9,
        "tracks": [
            "Wrists of Kings",
            "Not in Rivers, but in Drops",
            "Dulcinea",
            "Over Root and Thorn",
            "1,000 Shards",
            "All Out of Time, All Into Space",
            "Holy Tears",
            "Firdous E Bareen",
            "Garden of Light"
        ]
    }
]