[
    {
        "id": "07fB2SZNaI4otc0eqMhJWN",
        "name": "Home",
        "duration_ms": 195861,
        "popularity": 50,
        "track_number": 1,
        "album": "Portraits",
        "album_release_date": "2015-06-01",
        "album_id": "4nNZ5UJCzhlfJbip0SDLI1"
    },
    {
        "id": "0aOT5OQeNPyZzGwwudbaYs",
        "name": "The Clown",
        "duration_ms": 247861,
        "popularity": 50,
        "track_number": 2,
        "album": "Portraits",
        "album_release_date": "2015-06-01",
        "album_id": "4nNZ5UJCzhlfJbip0SDLI1"
    },
    {
        "id": "0UCU2uiUBfToI9EDdrS6aJ",
        "name": "Rituals",
        "duration_ms": 266839,
        "popularity": 40,
        "track_number": 3,
        "album": "Portraits",
        "album_release_date": "2015-06-01",
        "album_id": "4nNZ5UJCzhlfJbip0SDLI1"
    },
    {
        "id": "0pAiyIHt9DyHOjWgF41kp6",
        "name": "Steal",
        "duration_ms": 219945,
        "popularity": 64,
        "track_number": 4,
        "album": "Portraits",
        "album_release_date": "2015-06-01",
        "album_id": "4nNZ5UJCzhlfJbip0SDLI1"
    },
    {
        "id": "4mYDWmlkTTZ2jmHukYppym",
        "name": "Wallflower",
        "duration_ms": 223269,
        "popularity": 41,
        "track_number": 5,
        "album": "Portraits",
        "album_release_date": "2015-06-01",
        "album_id": "4nNZ5UJCzhlfJbip0SDLI1"
    },
    {
        "id": "3xaGXkbtFi7n5yDKdgBmTM",
        "name": "Say More",
        "duration_ms": 263581,
        "popularity": 39,
        "track_number": 6,
        "album": "Portraits",
        "album_release_date": "2015-06-01",
        "album_id": "4nNZ5UJCzhlfJbip0SDLI1"
    },
    {
        "id": "0cry75hK8X1CnzKBFMxrNg",
        "name": "Raincoats",
        "duration_ms": 277726,
        "popularity": 41,
        "track_number": 7,
        "album": "Portraits",
        "album_release_date": "2015-06-01",
        "album_id": "4nNZ5UJCzhlfJbip0SDLI1"
    },
    {
        "id": "6VNooTY5w9A9wg1YUsEbKB",
        "name": "Midas",
        "duration_ms": 218357,
        "popularity": 65,
        "track_number": 8,
        "album": "Portraits",
        "album_release_date": "2015-06-01",
        "album_id": "4nNZ5UJCzhlfJbip0SDLI1"
    },
    {
        "id": "2h3VovOKaebUKvhhdE0I5U",
        "name": "Natural Fools",
        "duration_ms": 339258,
        "popularity": 55,
        "track_number": 9,
        "album": "Portraits",
        "album_release_date": "2015-06-01",
        "album_id": "4nNZ5UJCzhlfJbip0SDLI1"
    },
    {
        "id": "0KFjTOGE68i5iz0IMVKJR4",
        "name": "Varkala",
        "duration_ms": 204023,
        "popularity": 46,
        "track_number": 10,
        "album": "Portraits",
        "album_release_date": "2015-06-01",
        "album_id": "4nNZ5UJCzhlfJbip0SDLI1"
    }
]