[
    {
        "id": "79ui4YL9awryb25pRruEDG",
        "name": "Wallowa Lake Monster",
        "duration_ms": 412174,
        "popularity": 48,
        "track_number": 1,
        "album": "The Greatest Gift",
        "album_release_date": "2017-11-24",
        "album_id": "57JZsVeZqBhukvZ9YOokyv"
    },
    {
        "id": "7giZV2M1cyuL4ZOm5fO8pL",
        "name": "Drawn to the Blood - Sufjan Stevens Remix",
        "duration_ms": 328821,
        "popularity": 36,
        "track_number": 2,
        "album": "The Greatest Gift",
        "album_release_date": "2017-11-24",
        "album_id": "57JZsVeZqBhukvZ9YOokyv"
    },
    {
        "id": "1GYJoepq4IpZDNhIKMP5jg",
        "name": "Death with Dignity - Helado Negro Remix",
        "duration_ms": 248374,
        "popularity": 36,
        "track_number": 3,
        "album": "The Greatest Gift",
        "album_release_date": "2017-11-24",
        "album_id": "57JZsVeZqBhukvZ9YOokyv"
    },
    {
        "id": "78dQ6DFCsdHl1KiiPynakk",
        "name": "John My Beloved - iPhone Demo",
        "duration_ms": 257199,
        "popularity": 36,
        "track_number": 4,
        "album": "The Greatest Gift",
        "album_release_date": "2017-11-24",
        "album_id": "57JZsVeZqBhukvZ9YOokyv"
    },
    {
        "id": "75apEWu95DEbqkrJi0xvkG",
        "name": "Drawn to the Blood - Fingerpicking Remix",
        "duration_ms": 121529,
        "popularity": 35,
        "track_number": 5,
        "album": "The Greatest Gift",
        "album_release_date": "2017-11-24",
        "album_id": "57JZsVeZqBhukvZ9YOokyv"
    },
    {
        "id": "2lFXZ6pE7Rb85JJAaiAueA",
        "name": "The Greatest Gift",
        "duration_ms": 111716,
        "popularity": 42,
        "track_number": 6,
        "album": "The Greatest Gift",
        "album_release_date": "2017-11-24",
        "album_id": "57JZsVeZqBhukvZ9YOokyv"
    },
    {
        "id": "75DAB2vMwJPnQRClAWrjya",
        "name": "Exploding Whale - Doveman Remix",
        "duration_ms": 327075,
        "popularity": 38,
        "track_number": 7,
        "album": "The Greatest Gift",
        "album_release_date": "2017-11-24",
        "album_id": "57JZsVeZqBhukvZ9YOokyv"
    },
    {
        "id": "58a0VZjpQQx1OaFHzxtkvZ",
        "name": "All of Me Wants All of You - Helado Negro Remix",
        "duration_ms": 204817,
        "popularity": 35,
        "track_number": 8,
        "album": "The Greatest Gift",
        "album_release_date": "2017-11-24",
        "album_id": "57JZsVeZqBhukvZ9YOokyv"
    },
    {
        "id": "6r3wQ06n9wziHPbtAl9ra0",
        "name": "Fourth of July - 900X Remix",
        "duration_ms": 408088,
        "popularity": 34,
        "track_number": 9,
        "album": "The Greatest Gift",
        "album_release_date": "2017-11-24",
        "album_id": "57JZsVeZqBhukvZ9YOokyv"
    },
    {
        "id": "3WqhCcRJEQ3gyBisLqe5GH",
        "name": "The Hidden River of My Life",
        "duration_ms": 244765,
        "popularity": 46,
        "track_number": 10,
        "album": "The Greatest Gift",
        "album_release_date": "2017-11-24",
        "album_id": "57JZsVeZqBhukvZ9YOokyv"
    },
    {
        "id": "7zDXgFJu9pfHv6jPVOJLJx",
        "name": "City of Roses",
        "duration_ms": 134404,
        "popularity": 45,
        "track_number": 11,
        "album": "The Greatest Gift",
        "album_release_date": "2017-11-24",
        "album_id": "57JZsVeZqBhukvZ9YOokyv"
    },
    {
        "id": "49ZBLuROH6b1D392uufzSv",
        "name": "Carrie & Lowell - iPhone Demo",
        "duration_ms": 112729,
        "popularity": 32,
        "track_number": 12,
        "album": "The Greatest Gift",
        "album_release_date": "2017-11-24",
        "album_id": "57JZsVeZqBhukvZ9YOokyv"
    }
]